diluvian/__init__.py
diluvian/__main__.py
diluvian/config.py
diluvian/diluvian.py
diluvian/network.py
diluvian/octrees.py
diluvian/postprocessing.py
diluvian/preprocessing.py
diluvian/regions.py
diluvian/training.py
diluvian/util.py
diluvian/volumes.py
diluvian/conf/cremi_datasets.toml
diluvian/conf/cremi_test_datasets.toml
diluvian/conf/default.toml
diluvian/third_party/LICENSE.txt
diluvian/third_party/__init__.py
diluvian/third_party/multi_gpu.py
diluvian-0.0.6.dist-info/DESCRIPTION.rst
diluvian-0.0.6.dist-info/METADATA
diluvian-0.0.6.dist-info/RECORD
diluvian-0.0.6.dist-info/WHEEL
diluvian-0.0.6.dist-info/entry_points.txt
diluvian-0.0.6.dist-info/metadata.json
diluvian-0.0.6.dist-info/top_level.txt
