Metadata-Version: 2.0
Name: diluvian
Version: 0.0.6
Summary: Flood filling networks for segmenting electron microscopy of neural tissue.
Home-page: https://github.com/aschampion/diluvian
Author: Andrew S. Champion
Author-email: andrew.champion@gmail.com
License: MIT license
Keywords: diluvian
Platform: UNKNOWN
Classifier: Development Status :: 2 - Pre-Alpha
Classifier: Intended Audience :: Science/Research
Classifier: License :: OSI Approved :: MIT License
Classifier: Natural Language :: English
Classifier: Programming Language :: Python :: 2
Classifier: Programming Language :: Python :: 2.7
Classifier: Topic :: Scientific/Engineering :: Bio-Informatics
Requires-Dist: h5py (>=2.6.0)
Requires-Dist: Keras (==2.0.8)
Requires-Dist: keras-contrib
Requires-Dist: matplotlib (==2.0.0)
Requires-Dist: networkx (==1.11)
Requires-Dist: neuroglancer (==0.0.8)
Requires-Dist: numpy (==1.13.1)
Requires-Dist: Pillow (==4.0.0)
Requires-Dist: pytoml (==0.1.11)
Requires-Dist: requests (==2.13.0)
Requires-Dist: scikit-image (==0.13.0)
Requires-Dist: scipy (==0.19.1)
Requires-Dist: six (==1.10.0)
Requires-Dist: tensorflow (==1.3.0)
Requires-Dist: tqdm (==4.19.1)
